{
  "alunos": [
    {
      "nome": "Beatriz",
      "apelido": "Silva",
      "curso": "Gestão",
      "anoCurricular": 1,
      "id": "604e"
    },
    {
      "id": "1",
      "nome": "João",
      "apelido": "Silva",
      "curso": "Informática",
      "anoCurricular": 2
    },
    {
      "id": "7115",
      "nome": "Ana",
      "apelido": "Costa",
      "curso": "Design",
      "anoCurricular": 3
    },
    {
      "id": "f67f",
      "nome": "Pedro",
      "apelido": "Martins",
      "curso": "Gestão",
      "anoCurricular": 2
    },
    {
      "id": "ab7b",
      "nome": "João",
      "apelido": "Soares",
      "curso": "Redes",
      "anoCurricular": 1
    }
  ],
  "cursos": [
    {
      "nomeDoCurso": "Engenharia Informática",
      "id": "f5e6"
    },
    {
      "nomeDoCurso": "Gestão",
      "id": "d5f4"
    },
    {
      "nomeDoCurso": "Design",
      "id": "b615"
    },
    {
      "id": 3,
      "nome": "Engenharia de Redes e Sistemas de Computadores"
    }
  ]
}